docker_overdose/__init__.py
docker_overdose/__main__.py
docker_overdose/base.py
docker_overdose/cli.py
docker_overdose/containermanager.py
docker_overdose-0.2.1.dist-info/LICENSE
docker_overdose-0.2.1.dist-info/METADATA
docker_overdose-0.2.1.dist-info/WHEEL
docker_overdose-0.2.1.dist-info/entry_points.txt
docker_overdose-0.2.1.dist-info/top_level.txt
docker_overdose-0.2.1.dist-info/RECORD
