Metadata-Version: 2.1
Name: docker-overdose
Version: 0.2.1
Summary: Awesome docker_overdose created by Diamino
Home-page: https://github.com/diamino/docker-overdose/
Author: diamino
License-File: LICENSE
Requires-Dist: docker
Provides-Extra: test
Requires-Dist: pytest ; extra == 'test'
Requires-Dist: coverage ; extra == 'test'
Requires-Dist: flake8 ; extra == 'test'
Requires-Dist: black ; extra == 'test'
Requires-Dist: isort ; extra == 'test'
Requires-Dist: pytest-cov ; extra == 'test'
Requires-Dist: mypy ; extra == 'test'
Requires-Dist: gitchangelog ; extra == 'test'
Requires-Dist: mkdocs ; extra == 'test'
